cflg/Base.py
cflg/CreateTables.py
cflg/FeatureFormation.py
cflg/FormFeaturesDF.py
cflg/ModelPerformance.py
cflg/VERSION
cflg/__init__.py
cflg/__version__.py
cflg/main.py
cflg/py.typed
NetLinkAnalyzer-1.0.0.dev0.dist-info/LICENSE.md
NetLinkAnalyzer-1.0.0.dev0.dist-info/METADATA
NetLinkAnalyzer-1.0.0.dev0.dist-info/WHEEL
NetLinkAnalyzer-1.0.0.dev0.dist-info/top_level.txt
NetLinkAnalyzer-1.0.0.dev0.dist-info/RECORD
