Metadata-Version: 2.1
Name: NetLinkAnalyzer
Version: 1.0.0.dev0
Summary: "The program for calculating features of links in large-scale networks and calculating characteristics of static graphs."
Author: Roman Neronov
Author-email: roman.nieronov@gmail.com
License: Other/Proprietary License
Classifier: Development Status :: 1 - Planning
Classifier: Environment :: Console
Classifier: Intended Audience :: Science/Research
Classifier: License :: Other/Proprietary License
Classifier: Natural Language :: English
Classifier: Operating System :: OS Independent
Classifier: Programming Language :: Python :: 3.8
Classifier: Programming Language :: Python :: 3.9
Classifier: Programming Language :: Python :: 3.10
Classifier: Programming Language :: Python :: 3.11
Classifier: Programming Language :: Python :: 3.12
Classifier: Topic :: Scientific/Engineering :: Artificial Intelligence
Requires-Python: >=3.8
License-File: LICENSE.md
Requires-Dist: python-dotenv >=0.5.1
Requires-Dist: ipython ==8.18.1
Requires-Dist: numpy ==1.26.2
Requires-Dist: pandas ==2.1.4
Requires-Dist: pydantic ==2.5.2
Requires-Dist: scikit-learn ==1.3.2
Requires-Dist: setuptools ==68.0.0
Requires-Dist: Jinja2 ==3.1.2
